src/__init__.py
src/aws_profile.py
aws_profiles-1.0.0.dist-info/entry_points.txt
aws_profiles-1.0.0.dist-info/WHEEL
aws_profiles-1.0.0.dist-info/METADATA
aws_profiles-1.0.0.dist-info/RECORD
