Metadata-Version: 2.1
Name: aws-profiles
Version: 1.0.0
Summary: Simple Script to list all named profiles in ~/.aws/config
Home-page: https://github.com/cloudshiftstrategies/aws-profiles
License: MIT
Keywords: aws,awscli,aws-cli
Author: Brian Peterson
Author-email: brian.peterson@cloudshift.cc
Requires-Python: >=3.9,<4.0
Classifier: License :: OSI Approved :: MIT License
Classifier: Programming Language :: Python :: 3
Classifier: Programming Language :: Python :: 3.10
Classifier: Programming Language :: Python :: 3.9
Project-URL: Repository, https://github.com/cloudshiftstrategies/aws-profiles
